create_vibe_app/__init__.py
create_vibe_app/main.py
create_vibe_app/templates/vibe-default/MAIN.md
create_vibe_app/templates/vibe-default/agent/design-manager.md
create_vibe_app/templates/vibe-default/agent/experience-depositor.md
create_vibe_app/templates/vibe-default/agent/implementation-executor.md
create_vibe_app/templates/vibe-default/agent/phase-router.md
create_vibe_app/templates/vibe-default/agent/requirement-manager.md
create_vibe_app/templates/vibe-default/code/README.md
create_vibe_app/templates/vibe-default/mcp/README.md
create_vibe_app/templates/vibe-default/reference/README.md
create_vibe_app/templates/vibe-default/requirement/INDEX.md
create_vibe_app/templates/vibe-default/requirement/completed/.gitkeep
create_vibe_app/templates/vibe-default/requirement/in-progress/.gitkeep
create_vibe_app/templates/vibe-default/skill/code-commit/SKILL.md
create_vibe_app/templates/vibe-default/skill/code-review/SKILL.md
create_vibe_app/templates/vibe-default/skill/design-create/SKILL.md
create_vibe_app/templates/vibe-default/skill/experience-record/SKILL.md
create_vibe_app/templates/vibe-default/skill/frontend-design/SKILL.md
create_vibe_app/templates/vibe-default/skill/req-create/SKILL.md
create_vibe_app/templates/vibe-default/skill/skill-creator/SKILL.md
create_vibe_app/templates/vibe-default/skill/test-create/SKILL.md
create_vibe_app/templates/vibe-default/skill/webapp-testing/SKILL.md
create_vibe_app/templates/vibe-default/skill/workspace-setup/SKILL.md
create_vibe_app/templates/vibe-default/wiki/api/README.md
create_vibe_app/templates/vibe-default/wiki/business/README.md
create_vibe_app/templates/vibe-default/wiki/design/README.md
create_vibe_app/templates/vibe-default/wiki/experience/README.md
create_vibe_app/templates/vibe-default/wiki/tech/README.md
create_vibe_app-0.1.0.dist-info/METADATA
create_vibe_app-0.1.0.dist-info/WHEEL
create_vibe_app-0.1.0.dist-info/entry_points.txt
create_vibe_app-0.1.0.dist-info/top_level.txt
create_vibe_app-0.1.0.dist-info/RECORD
