Metadata-Version: 2.4
Name: create-vibe-app
Version: 0.1.0
Summary: A CLI tool to scaffold Vibe Coding projects
Author-email: Vibe Coding Team <haoshaochun@gmail.com>
Classifier: Programming Language :: Python :: 3
Classifier: License :: OSI Approved :: MIT License
Classifier: Operating System :: OS Independent
Requires-Python: >=3.8
Requires-Dist: typer[all]
Requires-Dist: rich
